mxdownloader/__init__.py
mxdownloader/cli_click.py
mxdownloader/cli_inq.py
mxdownloader/functions.py
mxdownloader/mdx.py
mxdownloader-1.0.1.dist-info/LICENSE
mxdownloader-1.0.1.dist-info/METADATA
mxdownloader-1.0.1.dist-info/WHEEL
mxdownloader-1.0.1.dist-info/entry_points.txt
mxdownloader-1.0.1.dist-info/top_level.txt
mxdownloader-1.0.1.dist-info/RECORD
