Metadata-Version: 2.1
Name: mxdownloader
Version: 1.0.1
Summary: Download Manga using the MangaDex API
Home-page: https://github.com/Hiro427/mxdownloader
Author: Jacob Rambarran
License: MIT
Classifier: Programming Language :: Python :: 3
Classifier: License :: OSI Approved :: MIT License
Classifier: Operating System :: OS Independent
License-File: LICENSE
Requires-Dist: altgraph==0.17.4
Requires-Dist: blessed==1.20.0
Requires-Dist: certifi==2024.8.30
Requires-Dist: charset-normalizer==3.3.2
Requires-Dist: click==8.1.7
Requires-Dist: clipboard==0.0.4
Requires-Dist: editor==1.6.6
Requires-Dist: idna==3.10
Requires-Dist: inquirer==3.4.0
Requires-Dist: inquirerpy==0.3.4
Requires-Dist: packaging==24.2
Requires-Dist: pfzy==0.3.4
Requires-Dist: prompt_toolkit==3.0.47
Requires-Dist: pyinstaller==6.11.1
Requires-Dist: pyinstaller-hooks-contrib==2024.10
Requires-Dist: pyperclip==1.9.0
Requires-Dist: PyQt6==6.8.0
Requires-Dist: PyQt6-Qt6==6.8.1
Requires-Dist: PyQt6_sip==13.9.1
Requires-Dist: ratelimit==2.2.1
Requires-Dist: readchar==4.2.0
Requires-Dist: requests==2.32.3
Requires-Dist: runs==1.2.2
Requires-Dist: setuptools==75.6.0
Requires-Dist: six==1.16.0
Requires-Dist: tqdm==4.66.5
Requires-Dist: urllib3==2.2.3
Requires-Dist: wcwidth==0.2.13
Requires-Dist: xmod==1.8.1
